{
  "current": 12836.0,
  "statistics": {
    "highest": 12836.0,
    "lowest": 12836.0,
    "average": 12836.0,
    "median": 12836.0,
    "volatility": 0.0
  },
  "trends": {
    "last_24h_change": 0,
    "last_hour_change": 0,
    "daily_high": 12836.0,
    "daily_low": 12836.0
  },
  "data_quality": {
    "total_data_points": 1,
    "data_completeness": 100.0,
    "last_updated": "2025-10-15T09:19:28.013344+05:30",
    "data_age_minutes": 0.2
  },
  "generated_at": "2025-10-15T09:19:38.456275+05:30"
}