{
  "current": 16136.0,
  "statistics": {
    "highest": 16136.0,
    "lowest": 16136.0,
    "average": 16136.0,
    "median": 16136.0,
    "volatility": 0.0
  },
  "trends": {
    "last_24h_change": 0,
    "last_hour_change": 0,
    "daily_high": 16136.0,
    "daily_low": 16136.0
  },
  "data_quality": {
    "total_data_points": 1,
    "data_completeness": 100.0,
    "last_updated": "2026-02-24T08:50:12.689988+05:30",
    "data_age_minutes": 0.2
  },
  "generated_at": "2026-02-24T08:50:21.800241+05:30"
}